Workbook

Sheet Start Here
B1: Your 2027 Budget & Finance Planner
B2: Take control of every dollar - in 10 minutes a week.
B4: 1. SETUP
B5: Open the 'Setup' tab. Enter your starting balance and your monthly budget for each category. Rename any category to fit your life - the whole workbook updates automatically.
B7: 2. LOG
B8: Each time you earn or spend, add a row on the 'Transactions' tab: date, description, pick a category from the dropdown, and the amount. The Type column fills itself in.
B10: 3. REVIEW
B11: Check the 'Dashboard' any time: income vs. spending per month, savings rate, and which categories are over budget (highlighted red).
B13: 4. GROW
B14: Track big goals on 'Savings Goals' (it tells you how much to save per month) and plan your way out of debt on 'Debt Payoff' (it tells you how many months until you're free).
B16: TIPS
B17: Only edit WHITE cells. Shaded cells contain formulas. Works in Microsoft Excel, Google Sheets (File > Import), Apple Numbers and LibreOffice. Make a copy each year!
B20: Thank you for your purchase! Personal use license - please do not resell or redistribute.

Sheet Dashboard
B1: 2027 Dashboard
B2: Updates automatically from your Transactions.
B4: Total income | C4: Total spent | D4: Net saved | E4: Savings rate | F4: Balance now
B5: =SUMIFS(Transactions!$F$5:$F$1004,Transactions!$E$5:$E$1004,"Income") | C5: =SUMIFS(Transactions!$F$5:$F$1004,Transactions!$E$5:$E$1004,"Expense") | D5: =B5-C5 | E5: =IF(B5=0,0,D5/B5) | F5: =Setup!C4+D5
I6: Budget YTD = monthly budget x months with activity
B7: Month | C7: Income | D7: Expenses | E7: Net | F7: Savings rate | G7: Running balance | I7: Category | J7: Budget YTD | K7: Actual | L7: Remaining | M7: % used
B8: Jan | C8: =SUMIFS(Transactions!$F$5:$F$1004,Transactions!$E$5:$E$1004,"Income",Transactions!$G$5:$G$1004,1) | D8: =SUMIFS(Transactions!$F$5:$F$1004,Transactions!$E$5:$E$1004,"Expense",Transactions!$G$5:$G$1004,1) | E8: =C8-D8 | F8: =IF(C8=0,0,E8/C8) | G8: =Setup!$C$4+E8 | I8: =Setup!B8 | J8: =Setup!C8*MAX(1,MAX(Transactions!$G$5:$G$1004)) | K8: =SUMIFS(Transactions!$F$5:$F$1004,Transactions!$D$5:$D$1004,I8) | L8: =J8-K8 | M8: =IF(J8=0,0,K8/J8)
B9: Feb | C9: =SUMIFS(Transactions!$F$5:$F$1004,Transactions!$E$5:$E$1004,"Income",Transactions!$G$5:$G$1004,2) | D9: =SUMIFS(Transactions!$F$5:$F$1004,Transactions!$E$5:$E$1004,"Expense",Transactions!$G$5:$G$1004,2) | E9: =C9-D9 | F9: =IF(C9=0,0,E9/C9) | G9: =G8+E9 | I9: =Setup!B9 | J9: =Setup!C9*MAX(1,MAX(Transactions!$G$5:$G$1004)) | K9: =SUMIFS(Transactions!$F$5:$F$1004,Transactions!$D$5:$D$1004,I9) | L9: =J9-K9 | M9: =IF(J9=0,0,K9/J9)
B10: Mar | C10: =SUMIFS(Transactions!$F$5:$F$1004,Transactions!$E$5:$E$1004,"Income",Transactions!$G$5:$G$1004,3) | D10: =SUMIFS(Transactions!$F$5:$F$1004,Transactions!$E$5:$E$1004,"Expense",Transactions!$G$5:$G$1004,3) | E10: =C10-D10 | F10: =IF(C10=0,0,E10/C10) | G10: =G9+E10 | I10: =Setup!B10 | J10: =Setup!C10*MAX(1,MAX(Transactions!$G$5:$G$1004)) | K10: =SUMIFS(Transactions!$F$5:$F$1004,Transactions!$D$5:$D$1004,I10) | L10: =J10-K10 | M10: =IF(J10=0,0,K10/J10)
B11: Apr | C11: =SUMIFS(Transactions!$F$5:$F$1004,Transactions!$E$5:$E$1004,"Income",Transactions!$G$5:$G$1004,4) | D11: =SUMIFS(Transactions!$F$5:$F$1004,Transactions!$E$5:$E$1004,"Expense",Transactions!$G$5:$G$1004,4) | E11: =C11-D11 | F11: =IF(C11=0,0,E11/C11) | G11: =G10+E11 | I11: =Setup!B11 | J11: =Setup!C11*MAX(1,MAX(Transactions!$G$5:$G$1004)) | K11: =SUMIFS(Transactions!$F$5:$F$1004,Transactions!$D$5:$D$1004,I11) | L11: =J11-K11 | M11: =IF(J11=0,0,K11/J11)
B12: May | C12: =SUMIFS(Transactions!$F$5:$F$1004,Transactions!$E$5:$E$1004,"Income",Transactions!$G$5:$G$1004,5) | D12: =SUMIFS(Transactions!$F$5:$F$1004,Transactions!$E$5:$E$1004,"Expense",Transactions!$G$5:$G$1004,5) | E12: =C12-D12 | F12: =IF(C12=0,0,E12/C12) | G12: =G11+E12 | I12: =Setup!B12 | J12: =Setup!C12*MAX(1,MAX(Transactions!$G$5:$G$1004)) | K12: =SUMIFS(Transactions!$F$5:$F$1004,Transactions!$D$5:$D$1004,I12) | L12: =J12-K12 | M12: =IF(J12=0,0,K12/J12)
B13: Jun | C13: =SUMIFS(Transactions!$F$5:$F$1004,Transactions!$E$5:$E$1004,"Income",Transactions!$G$5:$G$1004,6) | D13: =SUMIFS(Transactions!$F$5:$F$1004,Transactions!$E$5:$E$1004,"Expense",Transactions!$G$5:$G$1004,6) | E13: =C13-D13 | F13: =IF(C13=0,0,E13/C13) | G13: =G12+E13 | I13: =Setup!B13 | J13: =Setup!C13*MAX(1,MAX(Transactions!$G$5:$G$1004)) | K13: =SUMIFS(Transactions!$F$5:$F$1004,Transactions!$D$5:$D$1004,I13) | L13: =J13-K13 | M13: =IF(J13=0,0,K13/J13)
B14: Jul | C14: =SUMIFS(Transactions!$F$5:$F$1004,Transactions!$E$5:$E$1004,"Income",Transactions!$G$5:$G$1004,7) | D14: =SUMIFS(Transactions!$F$5:$F$1004,Transactions!$E$5:$E$1004,"Expense",Transactions!$G$5:$G$1004,7) | E14: =C14-D14 | F14: =IF(C14=0,0,E14/C14) | G14: =G13+E14 | I14: =Setup!B14 | J14: =Setup!C14*MAX(1,MAX(Transactions!$G$5:$G$1004)) | K14: =SUMIFS(Transactions!$F$5:$F$1004,Transactions!$D$5:$D$1004,I14) | L14: =J14-K14 | M14: =IF(J14=0,0,K14/J14)
B15: Aug | C15: =SUMIFS(Transactions!$F$5:$F$1004,Transactions!$E$5:$E$1004,"Income",Transactions!$G$5:$G$1004,8) | D15: =SUMIFS(Transactions!$F$5:$F$1004,Transactions!$E$5:$E$1004,"Expense",Transactions!$G$5:$G$1004,8) | E15: =C15-D15 | F15: =IF(C15=0,0,E15/C15) | G15: =G14+E15 | I15: =Setup!B15 | J15: =Setup!C15*MAX(1,MAX(Transactions!$G$5:$G$1004)) | K15: =SUMIFS(Transactions!$F$5:$F$1004,Transactions!$D$5:$D$1004,I15) | L15: =J15-K15 | M15: =IF(J15=0,0,K15/J15)
B16: Sep | C16: =SUMIFS(Transactions!$F$5:$F$1004,Transactions!$E$5:$E$1004,"Income",Transactions!$G$5:$G$1004,9) | D16: =SUMIFS(Transactions!$F$5:$F$1004,Transactions!$E$5:$E$1004,"Expense",Transactions!$G$5:$G$1004,9) | E16: =C16-D16 | F16: =IF(C16=0,0,E16/C16) | G16: =G15+E16 | I16: =Setup!B16 | J16: =Setup!C16*MAX(1,MAX(Transactions!$G$5:$G$1004)) | K16: =SUMIFS(Transactions!$F$5:$F$1004,Transactions!$D$5:$D$1004,I16) | L16: =J16-K16 | M16: =IF(J16=0,0,K16/J16)
B17: Oct | C17: =SUMIFS(Transactions!$F$5:$F$1004,Transactions!$E$5:$E$1004,"Income",Transactions!$G$5:$G$1004,10) | D17: =SUMIFS(Transactions!$F$5:$F$1004,Transactions!$E$5:$E$1004,"Expense",Transactions!$G$5:$G$1004,10) | E17: =C17-D17 | F17: =IF(C17=0,0,E17/C17) | G17: =G16+E17 | I17: =Setup!B17 | J17: =Setup!C17*MAX(1,MAX(Transactions!$G$5:$G$1004)) | K17: =SUMIFS(Transactions!$F$5:$F$1004,Transactions!$D$5:$D$1004,I17) | L17: =J17-K17 | M17: =IF(J17=0,0,K17/J17)
B18: Nov | C18: =SUMIFS(Transactions!$F$5:$F$1004,Transactions!$E$5:$E$1004,"Income",Transactions!$G$5:$G$1004,11) | D18: =SUMIFS(Transactions!$F$5:$F$1004,Transactions!$E$5:$E$1004,"Expense",Transactions!$G$5:$G$1004,11) | E18: =C18-D18 | F18: =IF(C18=0,0,E18/C18) | G18: =G17+E18 | I18: =Setup!B18 | J18: =Setup!C18*MAX(1,MAX(Transactions!$G$5:$G$1004)) | K18: =SUMIFS(Transactions!$F$5:$F$1004,Transactions!$D$5:$D$1004,I18) | L18: =J18-K18 | M18: =IF(J18=0,0,K18/J18)
B19: Dec | C19: =SUMIFS(Transactions!$F$5:$F$1004,Transactions!$E$5:$E$1004,"Income",Transactions!$G$5:$G$1004,12) | D19: =SUMIFS(Transactions!$F$5:$F$1004,Transactions!$E$5:$E$1004,"Expense",Transactions!$G$5:$G$1004,12) | E19: =C19-D19 | F19: =IF(C19=0,0,E19/C19) | G19: =G18+E19 | I19: =Setup!B19 | J19: =Setup!C19*MAX(1,MAX(Transactions!$G$5:$G$1004)) | K19: =SUMIFS(Transactions!$F$5:$F$1004,Transactions!$D$5:$D$1004,I19) | L19: =J19-K19 | M19: =IF(J19=0,0,K19/J19)
B20: TOTAL | C20: =SUM(C8:C19) | D20: =SUM(D8:D19) | E20: =SUM(E8:E19) | F20: =IF(C20=0,0,E20/C20) | G20: =G19 | I20: =Setup!B20 | J20: =Setup!C20*MAX(1,MAX(Transactions!$G$5:$G$1004)) | K20: =SUMIFS(Transactions!$F$5:$F$1004,Transactions!$D$5:$D$1004,I20) | L20: =J20-K20 | M20: =IF(J20=0,0,K20/J20)
I21: =Setup!B21 | J21: =Setup!C21*MAX(1,MAX(Transactions!$G$5:$G$1004)) | K21: =SUMIFS(Transactions!$F$5:$F$1004,Transactions!$D$5:$D$1004,I21) | L21: =J21-K21 | M21: =IF(J21=0,0,K21/J21)
I22: =Setup!B22 | J22: =Setup!C22*MAX(1,MAX(Transactions!$G$5:$G$1004)) | K22: =SUMIFS(Transactions!$F$5:$F$1004,Transactions!$D$5:$D$1004,I22) | L22: =J22-K22 | M22: =IF(J22=0,0,K22/J22)
I23: =Setup!B23 | J23: =Setup!C23*MAX(1,MAX(Transactions!$G$5:$G$1004)) | K23: =SUMIFS(Transactions!$F$5:$F$1004,Transactions!$D$5:$D$1004,I23) | L23: =J23-K23 | M23: =IF(J23=0,0,K23/J23)
I24: =Setup!B24 | J24: =Setup!C24*MAX(1,MAX(Transactions!$G$5:$G$1004)) | K24: =SUMIFS(Transactions!$F$5:$F$1004,Transactions!$D$5:$D$1004,I24) | L24: =J24-K24 | M24: =IF(J24=0,0,K24/J24)
I25: =Setup!B25 | J25: =Setup!C25*MAX(1,MAX(Transactions!$G$5:$G$1004)) | K25: =SUMIFS(Transactions!$F$5:$F$1004,Transactions!$D$5:$D$1004,I25) | L25: =J25-K25 | M25: =IF(J25=0,0,K25/J25)

Sheet Setup
B1: Setup
B2: Edit the white cells. Everything else updates automatically.
B4: Starting balance (Jan 1) | C4: 2500
B5: Monthly savings target | C5: 500
B7: Expense category | C7: Monthly budget | E7: Income category | F7: Expected / month | H7: All categories (auto)
B8: Rent / Mortgage | C8: 1200 | E8: Salary | F8: 4000 | H8: =E8
B9: Utilities | C9: 180 | E9: Side Hustle | F9: 0 | H9: =E9
B10: Groceries | C10: 450 | E10: Freelance | F10: 0 | H10: =E10
B11: Transport | C11: 200 | E11: Investments | F11: 0 | H11: =E11
B12: Insurance | C12: 150 | E12: Gifts | F12: 0 | H12: =E12
B13: Phone & Internet | C13: 90 | E13: Other Income | F13: 0 | H13: =E13
B14: Dining Out | C14: 150 | E14: TOTAL | F14: =SUM(F8:F13) | H14: =B8
B15: Entertainment | C15: 80 | H15: =B9
B16: Subscriptions | C16: 40 | H16: =B10
B17: Shopping | C17: 120 | H17: =B11
B18: Health | C18: 60 | H18: =B12
B19: Personal Care | C19: 50 | H19: =B13
B20: Education | C20: 30 | H20: =B14
B21: Gifts & Donations | C21: 50 | H21: =B15
B22: Travel | C22: 100 | H22: =B16
B23: Debt Payments | C23: 250 | H23: =B17
B24: Savings Transfer | C24: 300 | H24: =B18
B25: Miscellaneous | C25: 50 | H25: =B19
B26: TOTAL | C26: =SUM(C8:C25) | H26: =B20
H27: =B21
H28: =B22
H29: =B23
H30: =B24
H31: =B25

Sheet Transactions
B1: Transactions
B2: One row per income or expense. Enter amounts as positive numbers.
B4: Date | C4: Description | D4: Category | E4: Type | F4: Amount | G4: Month
B5: 46388 | C5: January paycheck | D5: Salary | E5: =IF(D5="","",IF(COUNTIF(Setup!$E$8:$E$13,D5)>0,"Income","Expense")) | F5: 4000 | G5: =IF(B5="","",MONTH(B5))
B6: 46389 | C6: Rent | D6: Rent / Mortgage | E6: =IF(D6="","",IF(COUNTIF(Setup!$E$8:$E$13,D6)>0,"Income","Expense")) | F6: 1200 | G6: =IF(B6="","",MONTH(B6))
B7: 46392 | C7: Weekly groceries | D7: Groceries | E7: =IF(D7="","",IF(COUNTIF(Setup!$E$8:$E$13,D7)>0,"Income","Expense")) | F7: 112.4 | G7: =IF(B7="","",MONTH(B7))
B8: 46395 | C8: Electric bill | D8: Utilities | E8: =IF(D8="","",IF(COUNTIF(Setup!$E$8:$E$13,D8)>0,"Income","Expense")) | F8: 86.15 | G8: =IF(B8="","",MONTH(B8))
B9: 46399 | C9: Logo design gig | D9: Freelance | E9: =IF(D9="","",IF(COUNTIF(Setup!$E$8:$E$13,D9)>0,"Income","Expense")) | F9: 350 | G9: =IF(B9="","",MONTH(B9))
B10: 46402 | C10: Dinner with friends | D10: Dining Out | E10: =IF(D10="","",IF(COUNTIF(Setup!$E$8:$E$13,D10)>0,"Income","Expense")) | F10: 64.8 | G10: =IF(B10="","",MONTH(B10))
E11: =IF(D11="","",IF(COUNTIF(Setup!$E$8:$E$13,D11)>0,"Income","Expense")) | G11: =IF(B11="","",MONTH(B11))
E12: =IF(D12="","",IF(COUNTIF(Setup!$E$8:$E$13,D12)>0,"Income","Expense")) | G12: =IF(B12="","",MONTH(B12))
E13: =IF(D13="","",IF(COUNTIF(Setup!$E$8:$E$13,D13)>0,"Income","Expense")) | G13: =IF(B13="","",MONTH(B13))
E14: =IF(D14="","",IF(COUNTIF(Setup!$E$8:$E$13,D14)>0,"Income","Expense")) | G14: =IF(B14="","",MONTH(B14))
E15: =IF(D15="","",IF(COUNTIF(Setup!$E$8:$E$13,D15)>0,"Income","Expense")) | G15: =IF(B15="","",MONTH(B15))
E16: =IF(D16="","",IF(COUNTIF(Setup!$E$8:$E$13,D16)>0,"Income","Expense")) | G16: =IF(B16="","",MONTH(B16))
E17: =IF(D17="","",IF(COUNTIF(Setup!$E$8:$E$13,D17)>0,"Income","Expense")) | G17: =IF(B17="","",MONTH(B17))
E18: =IF(D18="","",IF(COUNTIF(Setup!$E$8:$E$13,D18)>0,"Income","Expense")) | G18: =IF(B18="","",MONTH(B18))
E19: =IF(D19="","",IF(COUNTIF(Setup!$E$8:$E$13,D19)>0,"Income","Expense")) | G19: =IF(B19="","",MONTH(B19))
E20: =IF(D20="","",IF(COUNTIF(Setup!$E$8:$E$13,D20)>0,"Income","Expense")) | G20: =IF(B20="","",MONTH(B20))
E21: =IF(D21="","",IF(COUNTIF(Setup!$E$8:$E$13,D21)>0,"Income","Expense")) | G21: =IF(B21="","",MONTH(B21))
E22: =IF(D22="","",IF(COUNTIF(Setup!$E$8:$E$13,D22)>0,"Income","Expense")) | G22: =IF(B22="","",MONTH(B22))
... E1004: =IF(D1004="","",IF(COUNTIF(Setup!$E$8:$E$13,D1004)>0,"Income","Expense")) | G1004: =IF(B1004="","",MONTH(B1004))

Sheet Savings Goals
B1: Savings Goals
B2: Name a goal, set a target and a deadline - see what to save each month.
B4: Goal | C4: Target | D4: Saved so far | E4: Progress | F4: Remaining | G4: Deadline | H4: Save per month
B5: Emergency fund | C5: 6000 | D5: 1500 | E5: =IF(C5="","",MIN(1,D5/C5)) | F5: =IF(C5="","",MAX(0,C5-D5)) | G5: 46752 | H5: =IF(OR(C5="",G5=""),"",IF(F5=0,0,F5/MAX(1,DATEDIF(TODAY(),G5,"m")+(G5<=TODAY()))))
B6: Vacation | C6: 2500 | D6: 400 | E6: =IF(C6="","",MIN(1,D6/C6)) | F6: =IF(C6="","",MAX(0,C6-D6)) | G6: 46569 | H6: =IF(OR(C6="",G6=""),"",IF(F6=0,0,F6/MAX(1,DATEDIF(TODAY(),G6,"m")+(G6<=TODAY()))))
B7: New laptop | C7: 1400 | D7: 200 | E7: =IF(C7="","",MIN(1,D7/C7)) | F7: =IF(C7="","",MAX(0,C7-D7)) | G7: 46508 | H7: =IF(OR(C7="",G7=""),"",IF(F7=0,0,F7/MAX(1,DATEDIF(TODAY(),G7,"m")+(G7<=TODAY()))))
E8: =IF(C8="","",MIN(1,D8/C8)) | F8: =IF(C8="","",MAX(0,C8-D8)) | H8: =IF(OR(C8="",G8=""),"",IF(F8=0,0,F8/MAX(1,DATEDIF(TODAY(),G8,"m")+(G8<=TODAY()))))
E9: =IF(C9="","",MIN(1,D9/C9)) | F9: =IF(C9="","",MAX(0,C9-D9)) | H9: =IF(OR(C9="",G9=""),"",IF(F9=0,0,F9/MAX(1,DATEDIF(TODAY(),G9,"m")+(G9<=TODAY()))))
E10: =IF(C10="","",MIN(1,D10/C10)) | F10: =IF(C10="","",MAX(0,C10-D10)) | H10: =IF(OR(C10="",G10=""),"",IF(F10=0,0,F10/MAX(1,DATEDIF(TODAY(),G10,"m")+(G10<=TODAY()))))
E11: =IF(C11="","",MIN(1,D11/C11)) | F11: =IF(C11="","",MAX(0,C11-D11)) | H11: =IF(OR(C11="",G11=""),"",IF(F11=0,0,F11/MAX(1,DATEDIF(TODAY(),G11,"m")+(G11<=TODAY()))))
E12: =IF(C12="","",MIN(1,D12/C12)) | F12: =IF(C12="","",MAX(0,C12-D12)) | H12: =IF(OR(C12="",G12=""),"",IF(F12=0,0,F12/MAX(1,DATEDIF(TODAY(),G12,"m")+(G12<=TODAY()))))
E13: =IF(C13="","",MIN(1,D13/C13)) | F13: =IF(C13="","",MAX(0,C13-D13)) | H13: =IF(OR(C13="",G13=""),"",IF(F13=0,0,F13/MAX(1,DATEDIF(TODAY(),G13,"m")+(G13<=TODAY()))))
E14: =IF(C14="","",MIN(1,D14/C14)) | F14: =IF(C14="","",MAX(0,C14-D14)) | H14: =IF(OR(C14="",G14=""),"",IF(F14=0,0,F14/MAX(1,DATEDIF(TODAY(),G14,"m")+(G14<=TODAY()))))
E15: =IF(C15="","",MIN(1,D15/C15)) | F15: =IF(C15="","",MAX(0,C15-D15)) | H15: =IF(OR(C15="",G15=""),"",IF(F15=0,0,F15/MAX(1,DATEDIF(TODAY(),G15,"m")+(G15<=TODAY()))))
E16: =IF(C16="","",MIN(1,D16/C16)) | F16: =IF(C16="","",MAX(0,C16-D16)) | H16: =IF(OR(C16="",G16=""),"",IF(F16=0,0,F16/MAX(1,DATEDIF(TODAY(),G16,"m")+(G16<=TODAY()))))

Sheet Debt Payoff
B1: Debt Payoff Planner
B2: Add extra payments and watch your debt-free date move closer.
B4: Debt | C4: Balance | D4: APR | E4: Min payment | F4: Extra / month | G4: Months to payoff | H4: Debt-free date | I4: Total interest
B5: Credit card | C5: 3200 | D5: 0.229 | E5: 95 | F5: 100 | G5: =IF(OR(C5="",C5=0),"",IF(D5=0,ROUNDUP(C5/(E5+F5),0),IF((E5+F5)<=C5*D5/12,"Payment too low",ROUNDUP(NPER(D5/12,-(E5+F5),C5),0)))) | H5: =IF(ISNUMBER(G5),EDATE(TODAY(),G5),"") | I5: =IF(ISNUMBER(G5),IF(D5=0,0,MAX(0,(E5+F5)*NPER(D5/12,-(E5+F5),C5)-C5)),"")
B6: Car loan | C6: 9800 | D6: 0.069 | E6: 280 | F6: 0 | G6: =IF(OR(C6="",C6=0),"",IF(D6=0,ROUNDUP(C6/(E6+F6),0),IF((E6+F6)<=C6*D6/12,"Payment too low",ROUNDUP(NPER(D6/12,-(E6+F6),C6),0)))) | H6: =IF(ISNUMBER(G6),EDATE(TODAY(),G6),"") | I6: =IF(ISNUMBER(G6),IF(D6=0,0,MAX(0,(E6+F6)*NPER(D6/12,-(E6+F6),C6)-C6)),"")
B7: Student loan | C7: 14500 | D7: 0.045 | E7: 160 | F7: 0 | G7: =IF(OR(C7="",C7=0),"",IF(D7=0,ROUNDUP(C7/(E7+F7),0),IF((E7+F7)<=C7*D7/12,"Payment too low",ROUNDUP(NPER(D7/12,-(E7+F7),C7),0)))) | H7: =IF(ISNUMBER(G7),EDATE(TODAY(),G7),"") | I7: =IF(ISNUMBER(G7),IF(D7=0,0,MAX(0,(E7+F7)*NPER(D7/12,-(E7+F7),C7)-C7)),"")
G8: =IF(OR(C8="",C8=0),"",IF(D8=0,ROUNDUP(C8/(E8+F8),0),IF((E8+F8)<=C8*D8/12,"Payment too low",ROUNDUP(NPER(D8/12,-(E8+F8),C8),0)))) | H8: =IF(ISNUMBER(G8),EDATE(TODAY(),G8),"") | I8: =IF(ISNUMBER(G8),IF(D8=0,0,MAX(0,(E8+F8)*NPER(D8/12,-(E8+F8),C8)-C8)),"")
G9: =IF(OR(C9="",C9=0),"",IF(D9=0,ROUNDUP(C9/(E9+F9),0),IF((E9+F9)<=C9*D9/12,"Payment too low",ROUNDUP(NPER(D9/12,-(E9+F9),C9),0)))) | H9: =IF(ISNUMBER(G9),EDATE(TODAY(),G9),"") | I9: =IF(ISNUMBER(G9),IF(D9=0,0,MAX(0,(E9+F9)*NPER(D9/12,-(E9+F9),C9)-C9)),"")
G10: =IF(OR(C10="",C10=0),"",IF(D10=0,ROUNDUP(C10/(E10+F10),0),IF((E10+F10)<=C10*D10/12,"Payment too low",ROUNDUP(NPER(D10/12,-(E10+F10),C10),0)))) | H10: =IF(ISNUMBER(G10),EDATE(TODAY(),G10),"") | I10: =IF(ISNUMBER(G10),IF(D10=0,0,MAX(0,(E10+F10)*NPER(D10/12,-(E10+F10),C10)-C10)),"")
G11: =IF(OR(C11="",C11=0),"",IF(D11=0,ROUNDUP(C11/(E11+F11),0),IF((E11+F11)<=C11*D11/12,"Payment too low",ROUNDUP(NPER(D11/12,-(E11+F11),C11),0)))) | H11: =IF(ISNUMBER(G11),EDATE(TODAY(),G11),"") | I11: =IF(ISNUMBER(G11),IF(D11=0,0,MAX(0,(E11+F11)*NPER(D11/12,-(E11+F11),C11)-C11)),"")
G12: =IF(OR(C12="",C12=0),"",IF(D12=0,ROUNDUP(C12/(E12+F12),0),IF((E12+F12)<=C12*D12/12,"Payment too low",ROUNDUP(NPER(D12/12,-(E12+F12),C12),0)))) | H12: =IF(ISNUMBER(G12),EDATE(TODAY(),G12),"") | I12: =IF(ISNUMBER(G12),IF(D12=0,0,MAX(0,(E12+F12)*NPER(D12/12,-(E12+F12),C12)-C12)),"")
G13: =IF(OR(C13="",C13=0),"",IF(D13=0,ROUNDUP(C13/(E13+F13),0),IF((E13+F13)<=C13*D13/12,"Payment too low",ROUNDUP(NPER(D13/12,-(E13+F13),C13),0)))) | H13: =IF(ISNUMBER(G13),EDATE(TODAY(),G13),"") | I13: =IF(ISNUMBER(G13),IF(D13=0,0,MAX(0,(E13+F13)*NPER(D13/12,-(E13+F13),C13)-C13)),"")
G14: =IF(OR(C14="",C14=0),"",IF(D14=0,ROUNDUP(C14/(E14+F14),0),IF((E14+F14)<=C14*D14/12,"Payment too low",ROUNDUP(NPER(D14/12,-(E14+F14),C14),0)))) | H14: =IF(ISNUMBER(G14),EDATE(TODAY(),G14),"") | I14: =IF(ISNUMBER(G14),IF(D14=0,0,MAX(0,(E14+F14)*NPER(D14/12,-(E14+F14),C14)-C14)),"")
B15: TOTAL | C15: =SUM(C5:C14) | E15: =SUM(E5:E14) | F15: =SUM(F5:F14) | G15: =IF(COUNT(G5:G14)=0,"",MAX(G5:G14)) | H15: =IF(ISNUMBER(G15),EDATE(TODAY(),G15),"") | I15: =SUM(I5:I14)
B17: Tip: put any extra money on the highest-APR debt first (avalanche) to pay the least interest.

Sheet Bill Tracker
B1: Bill Tracker
B2: List recurring bills, then type x in each month once paid.
B4: Bill | C4: Due day | D4: Amount | E4: Jan | F4: Feb | G4: Mar | H4: Apr | I4: May | J4: Jun | K4: Jul | L4: Aug | M4: Sep | N4: Oct | O4: Nov | P4: Dec
B5: Rent | C5: 1 | D5: 1200
B6: Electric | C6: 15 | D6: 90
B7: Phone | C7: 20 | D7: 55
B8: Streaming | C8: 3 | D8: 15.99
